ausbildungsnachweise_utils/__init__.py
ausbildungsnachweise_utils/__main__.py
ausbildungsnachweise_utils/processor.py
ausbildungsnachweise_utils/starter.py
ausbildungsnachweise_utils-0.0.8.dist-info/METADATA
ausbildungsnachweise_utils-0.0.8.dist-info/WHEEL
ausbildungsnachweise_utils-0.0.8.dist-info/entry_points.txt
ausbildungsnachweise_utils-0.0.8.dist-info/top_level.txt
ausbildungsnachweise_utils-0.0.8.dist-info/RECORD
